argparse_from_jsonschema.py
argparse_from_jsonschema-0.0.6.dist-info/LICENSE
argparse_from_jsonschema-0.0.6.dist-info/METADATA
argparse_from_jsonschema-0.0.6.dist-info/WHEEL
argparse_from_jsonschema-0.0.6.dist-info/entry_points.txt
argparse_from_jsonschema-0.0.6.dist-info/top_level.txt
argparse_from_jsonschema-0.0.6.dist-info/RECORD
