Metadata-Version: 2.1
Name: argparse-from-jsonschema
Version: 0.0.6
Summary: Parse Argument with JSON Schema
Home-page: https://github.com/LeConTesteur/argparse-from-jsonschema
Author: LeConTesteur
Keywords: Argparse,jsonschema,Argument Schema,data validation,json,validation,command,line,parser,parsing
License-File: LICENSE
